aiota2/__init__.py
aiota2/client.py
aiota2/datamodel.py
aiota2/exceptions.py
aiota2-1.0.1.dist-info/LICENSE
aiota2-1.0.1.dist-info/METADATA
aiota2-1.0.1.dist-info/WHEEL
aiota2-1.0.1.dist-info/top_level.txt
aiota2-1.0.1.dist-info/RECORD
