Metadata-Version: 2.1
Name: aiota2
Version: 1.0.1
Summary: Asynchronous python interface for <OPENDOTA/> API
Author: flsoap
Project-URL: Homepage, https://github.com/FilinSep/aiota2
Project-URL: Issues, https://github.com/FilinSep/aiota2/issues
Classifier: Programming Language :: Python :: 3
Classifier: License :: OSI Approved :: MIT License
Classifier: Operating System :: OS Independent
Requires-Python: >=3.8
License-File: LICENSE
